odoo/addons/coupon_domain_product_discount/README.rst
odoo/addons/coupon_domain_product_discount/__init__.py
odoo/addons/coupon_domain_product_discount/__manifest__.py
odoo/addons/coupon_domain_product_discount/i18n/coupon_domain_product_discount.pot
odoo/addons/coupon_domain_product_discount/i18n/es.po
odoo/addons/coupon_domain_product_discount/models/__init__.py
odoo/addons/coupon_domain_product_discount/models/coupon_reward.py
odoo/addons/coupon_domain_product_discount/models/coupon_rule.py
odoo/addons/coupon_domain_product_discount/readme/CONTRIBUTORS.rst
odoo/addons/coupon_domain_product_discount/readme/DESCRIPTION.rst
odoo/addons/coupon_domain_product_discount/readme/USAGE.rst
odoo/addons/coupon_domain_product_discount/report/sale_coupon_report_template.xml
odoo/addons/coupon_domain_product_discount/static/description/icon.png
odoo/addons/coupon_domain_product_discount/static/description/index.html
odoo/addons/coupon_domain_product_discount/tests/__init__.py
odoo/addons/coupon_domain_product_discount/tests/test_domain_product_discount.py
odoo/addons/coupon_domain_product_discount/views/coupon_program_views.xml
odoo_addon_coupon_domain_product_discount-15.0.1.1.1.2.dist-info/METADATA
odoo_addon_coupon_domain_product_discount-15.0.1.1.1.2.dist-info/WHEEL
odoo_addon_coupon_domain_product_discount-15.0.1.1.1.2.dist-info/top_level.txt
odoo_addon_coupon_domain_product_discount-15.0.1.1.1.2.dist-info/RECORD
